setup.py
enio_package.egg-info/PKG-INFO
enio_package.egg-info/SOURCES.txt
enio_package.egg-info/dependency_links.txt
enio_package.egg-info/requires.txt
enio_package.egg-info/top_level.txt
invoicing/__init__.py
invoicing/invoice.py